README.md
setup.cfg
setup.py
pyoml/__init__.py
pyoml.egg-info/PKG-INFO
pyoml.egg-info/SOURCES.txt
pyoml.egg-info/dependency_links.txt
pyoml.egg-info/top_level.txt
pyoml/fuzzy/__init__.py
pyoml/fuzzy/membership.py
pyoml/fuzzy/tests/__init__.py
pyoml/fuzzy/tests/test_membership.py